xmonkey_lidy/__init__.py
xmonkey_lidy/cli.py
xmonkey_lidy/downloader.py
xmonkey_lidy/matcher.py
xmonkey_lidy/utils.py
xmonkey_lidy/data/spdx_exclusions.json
xmonkey_lidy/data/spdx_license_patterns.json
xmonkey_lidy/data/spdx_licenses.json
xmonkey_lidy-1.0.13.dist-info/LICENSE
xmonkey_lidy-1.0.13.dist-info/METADATA
xmonkey_lidy-1.0.13.dist-info/WHEEL
xmonkey_lidy-1.0.13.dist-info/entry_points.txt
xmonkey_lidy-1.0.13.dist-info/top_level.txt
xmonkey_lidy-1.0.13.dist-info/RECORD
